<annotation>
	<folder />
	<filename>00012_00022_00000_png.rf.566792ac1c8fd5c121b0be894d908302.jpg</filename>
	<path>00012_00022_00000_png.rf.566792ac1c8fd5c121b0be894d908302.jpg</path>
	<source>
		<database>roboflow.ai</database>
	</source>
	<size>
		<width>640</width>
		<height>640</height>
		<depth>3</depth>
	</size>
	<segmented>0</segmented>
	<object>
		<name>Main Road</name>
		<pose>Unspecified</pose>
		<truncated>0</truncated>
		<difficult>0</difficult>
		<occluded>0</occluded>
		<bndbox>
			<xmin>114</xmin>
			<xmax>547</xmax>
			<ymin>114</ymin>
			<ymax>547</ymax>
		</bndbox>
	</object>
</annotation>