<annotation>
	<folder />
	<filename>00013_00046_00000_png.rf.993b888aaac7ba715c5c8d3c035ed961.jpg</filename>
	<path>00013_00046_00000_png.rf.993b888aaac7ba715c5c8d3c035ed961.jpg</path>
	<source>
		<database>roboflow.ai</database>
	</source>
	<size>
		<width>640</width>
		<height>640</height>
		<depth>3</depth>
	</size>
	<segmented>0</segmented>
	<object>
		<name>Give Way</name>
		<pose>Unspecified</pose>
		<truncated>0</truncated>
		<difficult>0</difficult>
		<occluded>0</occluded>
		<bndbox>
			<xmin>121</xmin>
			<xmax>541</xmax>
			<ymin>99</ymin>
			<ymax>559</ymax>
		</bndbox>
	</object>
</annotation>