<annotation>
	<folder />
	<filename>00013_00054_00018_png.rf.664338045831aa1e7418647df93d9190.jpg</filename>
	<path>00013_00054_00018_png.rf.664338045831aa1e7418647df93d9190.jpg</path>
	<source>
		<database>roboflow.ai</database>
	</source>
	<size>
		<width>640</width>
		<height>640</height>
		<depth>3</depth>
	</size>
	<segmented>0</segmented>
	<object>
		<name>Give Way</name>
		<pose>Unspecified</pose>
		<truncated>0</truncated>
		<difficult>0</difficult>
		<occluded>0</occluded>
		<bndbox>
			<xmin>60</xmin>
			<xmax>588</xmax>
			<ymin>63</ymin>
			<ymax>586</ymax>
		</bndbox>
	</object>
</annotation>