<annotation>
	<folder />
	<filename>00014_00021_00002_png.rf.e852d8b89cea5ccc5c06d9a0072585a2.jpg</filename>
	<path>00014_00021_00002_png.rf.e852d8b89cea5ccc5c06d9a0072585a2.jpg</path>
	<source>
		<database>roboflow.ai</database>
	</source>
	<size>
		<width>640</width>
		<height>640</height>
		<depth>3</depth>
	</size>
	<segmented>0</segmented>
	<object>
		<name>STOP</name>
		<pose>Unspecified</pose>
		<truncated>0</truncated>
		<difficult>0</difficult>
		<occluded>0</occluded>
		<bndbox>
			<xmin>121</xmin>
			<xmax>541</xmax>
			<ymin>101</ymin>
			<ymax>521</ymax>
		</bndbox>
	</object>
</annotation>