<annotation>
	<folder />
	<filename>00017_00035_00010_png.rf.ea4a070de62fb0e1b1a8771f9e605cbd.jpg</filename>
	<path>00017_00035_00010_png.rf.ea4a070de62fb0e1b1a8771f9e605cbd.jpg</path>
	<source>
		<database>roboflow.ai</database>
	</source>
	<size>
		<width>640</width>
		<height>640</height>
		<depth>3</depth>
	</size>
	<segmented>0</segmented>
	<object>
		<name>No Entry</name>
		<pose>Unspecified</pose>
		<truncated>0</truncated>
		<difficult>0</difficult>
		<occluded>0</occluded>
		<bndbox>
			<xmin>129</xmin>
			<xmax>534</xmax>
			<ymin>129</ymin>
			<ymax>534</ymax>
		</bndbox>
	</object>
</annotation>