<annotation>
	<folder></folder>
	<filename>00035_00024_00026_png.rf.82b3766bb8e9a184d5a52e8a24b6ef04.jpg</filename>
	<path>00035_00024_00026_png.rf.82b3766bb8e9a184d5a52e8a24b6ef04.jpg</path>
	<source>
		<database>roboflow.ai</database>
	</source>
	<size>
		<width>416</width>
		<height>416</height>
		<depth>3</depth>
	</size>
	<segmented>0</segmented>
	<object>
		<name>AheadOnly</name>
		<pose>Unspecified</pose>
		<truncated>0</truncated>
		<difficult>0</difficult>
		<occluded>0</occluded>
		<bndbox>
			<xmin>43</xmin>
			<xmax>376</xmax>
			<ymin>47</ymin>
			<ymax>380</ymax>
		</bndbox>
	</object>
</annotation>
