<annotation>
	<folder />
	<filename>00133_png.rf.8fbe45828c5392a17c1c349b0a47c1dd.jpg</filename>
	<path>00133_png.rf.8fbe45828c5392a17c1c349b0a47c1dd.jpg</path>
	<source>
		<database>roboflow.ai</database>
	</source>
	<size>
		<width>640</width>
		<height>640</height>
		<depth>3</depth>
	</size>
	<segmented>0</segmented>
	<object>
		<name>Give Way</name>
		<pose>Unspecified</pose>
		<truncated>0</truncated>
		<difficult>0</difficult>
		<occluded>0</occluded>
		<bndbox>
			<xmin>69</xmin>
			<xmax>584</xmax>
			<ymin>77</ymin>
			<ymax>579</ymax>
		</bndbox>
	</object>
</annotation>