<annotation>
	<folder />
	<filename>03882_png.rf.f3d097d7e4ff8c69081dc70108097798.jpg</filename>
	<path>03882_png.rf.f3d097d7e4ff8c69081dc70108097798.jpg</path>
	<source>
		<database>roboflow.ai</database>
	</source>
	<size>
		<width>640</width>
		<height>640</height>
		<depth>3</depth>
	</size>
	<segmented>0</segmented>
	<object>
		<name>Main Road</name>
		<pose>Unspecified</pose>
		<truncated>0</truncated>
		<difficult>0</difficult>
		<occluded>0</occluded>
		<bndbox>
			<xmin>105</xmin>
			<xmax>554</xmax>
			<ymin>99</ymin>
			<ymax>559</ymax>
		</bndbox>
	</object>
</annotation>