<annotation>
	<filename>autosave10_10_2012_12_50_11_0.jpg</filename>
	<source>
		<database>Unknown</database>
	</source>
	<size>
		<width>1280</width>
		<height>720</height>
		<depth>3</depth>
	</size>
	<segmented>0</segmented>
	<object>
		<name>One-Way Traffic</name>
		<pose>Unspecified</pose>
		<truncated>0</truncated>
		<difficult>0</difficult>
		<bndbox>
			<xmin>888</xmin>
			<ymin>111</ymin>
			<xmax>948</xmax>
			<ymax>160</ymax>
		</bndbox>
	</object>
	<object>
		<name>Pedestrian Crossing</name>
		<pose>Unspecified</pose>
		<truncated>0</truncated>
		<difficult>0</difficult>
		<bndbox>
			<xmin>899</xmin>
			<ymin>231</ymin>
			<xmax>938</xmax>
			<ymax>303</ymax>
		</bndbox>
	</object>
</annotation>