<annotation>
	<folder>test</folder>
	<filename>autosave09_11_2012_09_05_25_1.jpg</filename>
	<path>C:\Users\USER\Desktop\sdp_images\test\autosave09_11_2012_09_05_25_1.jpg</path>
	<source>
		<database>Unknown</database>
	</source>
	<size>
		<width>1280</width>
		<height>720</height>
		<depth>3</depth>
	</size>
	<segmented>0</segmented>
	<object>
		<name>Turn Left</name>
		<pose>Unspecified</pose>
		<truncated>0</truncated>
		<difficult>0</difficult>
		<bndbox>
			<xmin>772</xmin>
			<ymin>417</ymin>
			<xmax>793</xmax>
			<ymax>445</ymax>
		</bndbox>
	</object>
<object>
		<name>speed_warning_40</name>
		<pose>Unspecified</pose>
		<truncated>0</truncated>
		<difficult>0</difficult>
		<bndbox>
			<xmin>831</xmin>
			<ymin>406</ymin>
			<xmax>847</xmax>
			<ymax>422</ymax>
		</bndbox>
	</object>
</annotation>