<annotation>
	<folder></folder>
	<filename>fake_night_402_png_jpg.rf.8ec0a3a8b1fdccfca5cf2cbf40b9268d.jpg</filename>
	<path>fake_night_402_png_jpg.rf.8ec0a3a8b1fdccfca5cf2cbf40b9268d.jpg</path>
	<source>
		<database>roboflow.ai</database>
	</source>
	<size>
		<width>384</width>
		<height>384</height>
		<depth>3</depth>
	</size>
	<segmented>0</segmented>
	<object>
		<name>Speed_limit_90</name>
		<pose>Unspecified</pose>
		<truncated>0</truncated>
		<difficult>0</difficult>
		<occluded>0</occluded>
		<bndbox>
			<xmin>266</xmin>
			<xmax>293</xmax>
			<ymin>206</ymin>
			<ymax>239</ymax>
		</bndbox>
	</object>
</annotation>
