<annotation>
	<filename>petunjuk-lokasi-putar-balik-58-_jpg.rf.3ded22e366e8e7aa1a19a696c30c9ac5.jpg</filename>
	<source>
		<database>Unknown</database>
	</source>
	<size>
		<width>640</width>
		<height>640</height>
		<depth>3</depth>
	</size>
	<segmented>0</segmented>
	<object>
		<name>U-turn</name>
		<pose>Unspecified</pose>
		<truncated>0</truncated>
		<difficult>0</difficult>
		<bndbox>
			<xmin>268</xmin>
			<ymin>199</ymin>
			<xmax>409</xmax>
			<ymax>429</ymax>
		</bndbox>
	</object>
</annotation>