<annotation>
	<filename>petunjuk-lokasi-putar-balik-86-_jpg.rf.e33f45b95e7d54fd65d63d60c8752133.jpg</filename>
	<source>
		<database>Unknown</database>
	</source>
	<size>
		<width>640</width>
		<height>640</height>
		<depth>3</depth>
	</size>
	<segmented>0</segmented>
	<object>
		<name>U-turn</name>
		<pose>Unspecified</pose>
		<truncated>0</truncated>
		<difficult>0</difficult>
		<bndbox>
			<xmin>309</xmin>
			<ymin>127</ymin>
			<xmax>462</xmax>
			<ymax>385</ymax>
		</bndbox>
	</object>
</annotation>