<annotation>
	<folder />
	<filename>PXL_20220605_165140754_jpg.rf.50593eff2efc9193c78ff4bada327a23.jpg</filename>
	<path>PXL_20220605_165140754_jpg.rf.50593eff2efc9193c78ff4bada327a23.jpg</path>
	<source>
		<database>roboflow.ai</database>
	</source>
	<size>
		<width>416</width>
		<height>416</height>
		<depth>3</depth>
	</size>
	<segmented>0</segmented>
	<object>
		<name>No Waiting</name>
		<pose>Unspecified</pose>
		<truncated>0</truncated>
		<difficult>0</difficult>
		<occluded>0</occluded>
		<bndbox>
			<xmin>176</xmin>
			<xmax>231</xmax>
			<ymin>134</ymin>
			<ymax>233</ymax>
		</bndbox>
	</object>
</annotation>